__init__.py
the_one_api/__init__.py
the_one_api/errors.py
the_one_api/movie.py
the_one_api/quote.py
the_one_api/_base/__init__.py
the_one_api/_base/_base.py
the_one_api/_base/_multiple_results.py
the_one_api/_base/_single_results.py
the_one_api_sdk_duke-0.0.0.dist-info/LICENSE.txt
the_one_api_sdk_duke-0.0.0.dist-info/METADATA
the_one_api_sdk_duke-0.0.0.dist-info/WHEEL
the_one_api_sdk_duke-0.0.0.dist-info/top_level.txt
the_one_api_sdk_duke-0.0.0.dist-info/RECORD
