Metadata-Version: 2.1
Name: the-one-api-sdk-duke
Version: 0.0.0
Summary: A Python SDK to aid interacting with The One API data.
Author-email: Heather Duke <heathernoelduke@gmail.com>
Project-URL: Homepage, https://github.com/hnduke/duke-sdk
Project-URL: Bug Tracker, https://github.com/hnduke/duke-sdk/issues
Classifier: Programming Language :: Python :: 3
Classifier: License :: OSI Approved :: MIT License
Classifier: Operating System :: OS Independent
Requires-Python: >=3.10
License-File: LICENSE.txt
Requires-Dist: requests (==2.30.0)
